{
	"$schema": "https://json.schemastore.org/tsconfig",
	"compilerOptions": {
		"outDir": "dist",
		"sourceMap": true,
		"skipLibCheck": false,
		"preserveSymlinks": true,
		"inlineSources": true,
		"strict": true,
		"strictPropertyInitialization": false,
		"jsx": "preserve",
		"incremental": true,
		"esModuleInterop": true,
		"noUncheckedIndexedAccess": true,
		"noPropertyAccessFromIndexSignature": true,
		"exactOptionalPropertyTypes": true,
		"plugins": [
			{
				"name": "typescript-eslint-language-service"
			}
		]
	},
	"typeAcquisition": {
		"enable": true
	},
	"compileOnSave": true,
	"include": [
		"**/*.js",
		"**/*.ts",
		"**/*.tsx",
		"**/*.mts"
	],
	"exclude": [
		"node_modules",
		"./dist/**",
		"./out/**"
	]
}